{"_type":"export","__export_format":4,"__export_date":"2022-11-04T15:36:09.868Z","__export_source":"insomnia.desktop.app:v2022.6.0","resources":[{"_id":"req_208cf3a2ed5e48e98893e493e9e1e73b","parentId":"fld_f9bf6c9383a641168b8bdf1aaa449405","modified":1667543987547,"created":1654352091459,"url":" {{ _.local_url }}/auth/login","name":"Login","description":"","method":"POST","body":{"mimeType":"application/json","text":"{\"email\":\"test@test.com\", \"password\":\"1234\"}"},"parameters":[],"headers":[{"name":"Content-Type","value":"application/json","id":"pair_c65a07a06d614eea8f290ce29d022de9"}],"authentication":{"type":"bearer","token":"","disabled":true},"metaSortKey":-1654352091459,"isPrivate":false,"settingStoreCookies":true,"settingSendCookies":true,"settingDisableRenderRequestBody":false,"settingEncodeUrl":true,"settingRebuildPath":true,"settingFollowRedirects":"global","_type":"request"},{"_id":"fld_f9bf6c9383a641168b8bdf1aaa449405","parentId":"wrk_ab3a60a83e424f5495ed585f24243571","modified":1654352076643,"created":1654352076643,"name":"Auth","description":"","environment":{},"environmentPropertyOrder":null,"metaSortKey":-1654352076643,"_type":"request_group"},{"_id":"wrk_ab3a60a83e424f5495ed585f24243571","parentId":null,"modified":1652996236174,"created":1586993601746,"name":"programacion1","description":"","scope":"collection","_type":"workspace"},{"_id":"req_bedecd8939ac4efe96aa4a1ebf93f0b7","parentId":"fld_f9bf6c9383a641168b8bdf1aaa449405","modified":1667541189511,"created":1654354543576,"url":" {{ _.local_url }}/auth/register","name":"Register","description":"","method":"POST","body":{"mimeType":"application/json","text":"{\n\t\"firstname\": \"test\",\n\t\"email\": \"testtesttest@test.com\",\n\t\"password\": \"1234\",\n\t\"admin\": 0\n}"},"parameters":[],"headers":[{"name":"Content-Type","value":"application/json","id":"pair_c65a07a06d614eea8f290ce29d022de9"}],"authentication":{},"metaSortKey":-1653652006572,"isPrivate":false,"settingStoreCookies":true,"settingSendCookies":true,"settingDisableRenderRequestBody":false,"settingEncodeUrl":true,"settingRebuildPath":true,"settingFollowRedirects":"global","_type":"request"},{"_id":"req_ff5cef5a0ecb4a538e206fc6354b693a","parentId":"fld_9c41f9ae1129465bbda853e610d056d6","modified":1657763228964,"created":1648782180071,"url":"  {{ _.local_url }}/users","name":"New","description":"","method":"POST","body":{"mimeType":"application/json","text":"{\n\t\"firstname\": \"a\",\n\t\"email\": \"la@gmail.com\",\n\t\"password\": 111234,\n\t\"admin\": 1\n}"},"parameters":[],"headers":[{"name":"Content-Type","value":"application/json","id":"pair_b4f14799bcfd438ba0cd89719fad6ec9"}],"authentication":{"disabled":false,"token":"{{token}}","type":"bearer"},"metaSortKey":-1580855454921,"isPrivate":false,"settingStoreCookies":true,"settingSendCookies":true,"settingDisableRenderRequestBody":false,"settingEncodeUrl":true,"settingRebuildPath":true,"settingFollowRedirects":"global","_type":"request"},{"_id":"fld_9c41f9ae1129465bbda853e610d056d6","parentId":"fld_cc3cf1d9e4df4665afdf069290da9d8b","modified":1652948776191,"created":1648782180061,"name":"Users","description":"","environment":{},"environmentPropertyOrder":null,"metaSortKey":-1648779884418,"_type":"request_group"},{"_id":"fld_cc3cf1d9e4df4665afdf069290da9d8b","parentId":"wrk_ab3a60a83e424f5495ed585f24243571","modified":1654978272104,"created":1586993639756,"name":"Data","description":"","environment":{},"environmentPropertyOrder":null,"metaSortKey":-1585703808823.25,"_type":"request_group"},{"_id":"req_b094f4f8d7f34b23baab2a5f715a9b13","parentId":"fld_9c41f9ae1129465bbda853e610d056d6","modified":1667540839321,"created":1648782180065,"url":"  {{ _.local_url }}/users","name":"All","description":"","method":"GET","body":{},"parameters":[],"headers":[],"authentication":{"disabled":false,"token":"{{token}}","type":"bearer","prefix":""},"metaSortKey":-1580855454917.875,"isPrivate":false,"settingStoreCookies":true,"settingSendCookies":true,"settingDisableRenderRequestBody":false,"settingEncodeUrl":true,"settingRebuildPath":true,"settingFollowRedirects":"global","_type":"request"},{"_id":"req_384f96f553ec45d688fbf3e9ebb0b54a","parentId":"fld_441ea83962d24eb1a3ae5b7873e2abb3","modified":1667543093434,"created":1586993639759,"url":"  {{ _.local_url }}/poems","name":"New","description":"","method":"POST","body":{"mimeType":"application/json","text":"{\n \"title\": \"hola\",\n \"content\": \"hola es un saludo fin\",\n\t\"userID\": 1\n}"},"parameters":[],"headers":[{"name":"Content-Type","value":"application/json","id":"pair_b4f14799bcfd438ba0cd89719fad6ec9"}],"authentication":{"disabled":false,"token":"{{token}}","type":"bearer"},"metaSortKey":-1649395144500,"isPrivate":false,"settingStoreCookies":true,"settingSendCookies":true,"settingDisableRenderRequestBody":false,"settingEncodeUrl":true,"settingRebuildPath":true,"settingFollowRedirects":"global","_type":"request"},{"_id":"fld_441ea83962d24eb1a3ae5b7873e2abb3","parentId":"fld_cc3cf1d9e4df4665afdf069290da9d8b","modified":1652948780492,"created":1648779884368,"name":"Poems","description":"","environment":{},"environmentPropertyOrder":null,"metaSortKey":-1648779884405.5,"_type":"request_group"},{"_id":"req_cfc91b7550194c2486a5dacacf38e39b","parentId":"fld_441ea83962d24eb1a3ae5b7873e2abb3","modified":1667542302906,"created":1586993639761,"url":" {{ _.local_url }}/poems","name":"All","description":"","method":"GET","body":{"mimeType":"application/json","text":""},"parameters":[],"headers":[{"name":"Content-Type","value":"application/json","id":"pair_7192e384c13f498daceafa4dbf9d1e04"}],"authentication":{"token":"{{token}}","type":"bearer","disabled":false},"metaSortKey":-1649395144475,"isPrivate":false,"settingStoreCookies":true,"settingSendCookies":true,"settingDisableRenderRequestBody":false,"settingEncodeUrl":true,"settingRebuildPath":true,"settingFollowRedirects":"global","_type":"request"},{"_id":"req_e2e3d965f3a54a8fac976203458fcec2","parentId":"fld_103a6652bb1d4f3d8b64dc1f13e2cc56","modified":1667543100673,"created":1649391725668,"url":"{{ _.local_url }}/reviews","name":"New","description":"","method":"POST","body":{"mimeType":"application/json","text":"{\n\t\"userID\": 1,\n\t\"poemID\" : 1,\n\t\"score\": 10,\n\t\"comment\": \"algo\"\n}"},"parameters":[],"headers":[{"name":"Content-Type","value":"application/json","id":"pair_0ff3f9b6e2564845aec7994736652d0e"}],"authentication":{"type":"bearer","token":"{{token}}"},"metaSortKey":-1652951921685,"isPrivate":false,"settingStoreCookies":true,"settingSendCookies":true,"settingDisableRenderRequestBody":false,"settingEncodeUrl":true,"settingRebuildPath":true,"settingFollowRedirects":"global","_type":"request"},{"_id":"fld_103a6652bb1d4f3d8b64dc1f13e2cc56","parentId":"fld_cc3cf1d9e4df4665afdf069290da9d8b","modified":1652948778646,"created":1649391699082,"name":"Reviews","description":"","environment":{},"environmentPropertyOrder":null,"metaSortKey":-1648779884393,"_type":"request_group"},{"_id":"req_a0ec7bd7907e4d2289926a16ed0b678f","parentId":"fld_103a6652bb1d4f3d8b64dc1f13e2cc56","modified":1667542350471,"created":1649394540427,"url":"{{ _.local_url }}/reviews","name":"All","description":"","method":"GET","body":{"mimeType":"application/json","text":"{\"page\": 1, \"per_page\":3}"},"parameters":[],"headers":[{"name":"Content-Type","value":"application/json","id":"pair_34a6d2f8a893480ab288f0f9fa57a510"}],"authentication":{"type":"bearer","token":"{{token}}"},"metaSortKey":-1649394728184,"isPrivate":false,"settingStoreCookies":true,"settingSendCookies":true,"settingDisableRenderRequestBody":false,"settingEncodeUrl":true,"settingRebuildPath":true,"settingFollowRedirects":"global","_type":"request"},{"_id":"env_b9956f67f3a62e3cdedc2d9a11a1049b8d354d8a","parentId":"wrk_ab3a60a83e424f5495ed585f24243571","modified":1657917956758,"created":1586993601771,"name":"Base Environment","data":{"local_url":"http://127.0.0.1:5000","token":""},"dataPropertyOrder":{"&":["local_url","token"]},"color":null,"isPrivate":false,"metaSortKey":1586993601771,"_type":"environment"},{"_id":"jar_b9956f67f3a62e3cdedc2d9a11a1049b8d354d8a","parentId":"wrk_ab3a60a83e424f5495ed585f24243571","modified":1586993601775,"created":1586993601775,"name":"Default Jar","cookies":[],"_type":"cookie_jar"},{"_id":"spc_37ea6b61a4ce4cd8b3268ddd9992fa8f","parentId":"wrk_ab3a60a83e424f5495ed585f24243571","modified":1591736877044,"created":1591736877044,"fileName":"Curso","contents":"","contentType":"yaml","_type":"api_spec"},{"_id":"env_d34505c6e1e24081a7887f69813a501f","parentId":"env_b9956f67f3a62e3cdedc2d9a11a1049b8d354d8a","modified":1667540456125,"created":1654978190116,"name":"Programación 1","data":{"local_url":"http://localhost:7000","token":"eyJ0eXAiOiJKV1QiLCJhbGciOiJIUzI1NiJ9.eyJmcmVzaCI6ZmFsc2UsImlhdCI6MTY2NzU0MDI3MywianRpIjoiZjZiOTRlZWQtNmNkMC00ZjdhLTkwN2ItNmQxOTQ1N2YyNDAyIiwidHlwZSI6ImFjY2VzcyIsInN1YiI6MSwibmJmIjoxNjY3NTQwMjczLCJleHAiOjE2Njc1NDM4NzMsImFkbWluIjpmYWxzZSwiaWQiOjEsImVtYWlsIjoidGVzdEB0ZXN0LmNvbSJ9.Uc4YM7T608lKHTq5bBv9l3iCH0vWX9gTqcTtpvfZmFE"},"dataPropertyOrder":{"&":["local_url","token"]},"color":null,"isPrivate":false,"metaSortKey":1654978190116,"_type":"environment"}]}